<?xml version="1.0" encoding="utf-8"?>
<ArrayOfDependency xmlns:xsi="http://www.w3.org/2001/XMLSchema-instance" xmlns:xsd="http://www.w3.org/2001/XMLSchema">
  <Dependency>
    <Id>1</Id>
    <DependentTask>2</DependentTask>
    <DependsOnTask>1</DependsOnTask>
  </Dependency>
  <Dependency>
    <Id>7</Id>
    <DependentTask>8</DependentTask>
    <DependsOnTask>6</DependsOnTask>
  </Dependency>
  <Dependency>
    <Id>8</Id>
    <DependentTask>8</DependentTask>
    <DependsOnTask>7</DependsOnTask>
  </Dependency>
  <Dependency>
    <Id>9</Id>
    <DependentTask>8</DependentTask>
    <DependsOnTask>2</DependsOnTask>
  </Dependency>
  <Dependency>
    <Id>17</Id>
    <DependentTask>12</DependentTask>
    <DependsOnTask>11</DependsOnTask>
  </Dependency>
  <Dependency>
    <Id>18</Id>
    <DependentTask>12</DependentTask>
    <DependsOnTask>6</DependsOnTask>
  </Dependency>
  <Dependency>
    <Id>19</Id>
    <DependentTask>12</DependentTask>
    <DependsOnTask>5</DependsOnTask>
  </Dependency>
  <Dependency>
    <Id>20</Id>
    <DependentTask>12</DependentTask>
    <DependsOnTask>4</DependsOnTask>
  </Dependency>
  <Dependency>
    <Id>21</Id>
    <DependentTask>13</DependentTask>
    <DependsOnTask>5</DependsOnTask>
  </Dependency>
  <Dependency>
    <Id>22</Id>
    <DependentTask>13</DependentTask>
    <DependsOnTask>6</DependsOnTask>
  </Dependency>
  <Dependency>
    <Id>23</Id>
    <DependentTask>13</DependentTask>
    <DependsOnTask>4</DependsOnTask>
  </Dependency>
  <Dependency>
    <Id>24</Id>
    <DependentTask>13</DependentTask>
    <DependsOnTask>12</DependsOnTask>
  </Dependency>
  <Dependency>
    <Id>27</Id>
    <DependentTask>16</DependentTask>
    <DependsOnTask>15</DependsOnTask>
  </Dependency>
  <Dependency>
    <Id>28</Id>
    <DependentTask>16</DependentTask>
    <DependsOnTask>2</DependsOnTask>
  </Dependency>
  <Dependency>
    <Id>29</Id>
    <DependentTask>16</DependentTask>
    <DependsOnTask>4</DependsOnTask>
  </Dependency>
  <Dependency>
    <Id>30</Id>
    <DependentTask>16</DependentTask>
    <DependsOnTask>5</DependsOnTask>
  </Dependency>
  <Dependency>
    <Id>31</Id>
    <DependentTask>16</DependentTask>
    <DependsOnTask>10</DependsOnTask>
  </Dependency>
  <Dependency>
    <Id>32</Id>
    <DependentTask>16</DependentTask>
    <DependsOnTask>1</DependsOnTask>
  </Dependency>
  <Dependency>
    <Id>33</Id>
    <DependentTask>16</DependentTask>
    <DependsOnTask>3</DependsOnTask>
  </Dependency>
  <Dependency>
    <Id>34</Id>
    <DependentTask>16</DependentTask>
    <DependsOnTask>2</DependsOnTask>
  </Dependency>
  <Dependency>
    <Id>35</Id>
    <DependentTask>20</DependentTask>
    <DependsOnTask>8</DependsOnTask>
  </Dependency>
  <Dependency>
    <Id>36</Id>
    <DependentTask>20</DependentTask>
    <DependsOnTask>2</DependsOnTask>
  </Dependency>
  <Dependency>
    <Id>37</Id>
    <DependentTask>20</DependentTask>
    <DependsOnTask>16</DependsOnTask>
  </Dependency>
  <Dependency>
    <Id>38</Id>
    <DependentTask>20</DependentTask>
    <DependsOnTask>19</DependsOnTask>
  </Dependency>
  <Dependency>
    <Id>39</Id>
    <DependentTask>20</DependentTask>
    <DependsOnTask>18</DependsOnTask>
  </Dependency>
  <Dependency>
    <Id>40</Id>
    <DependentTask>20</DependentTask>
    <DependsOnTask>17</DependsOnTask>
  </Dependency>
  <Dependency>
    <Id>42</Id>
    <DependentTask>0</DependentTask>
    <DependsOnTask>5</DependsOnTask>
  </Dependency>
  <Dependency>
    <Id>43</Id>
    <DependentTask>0</DependentTask>
    <DependsOnTask>8</DependsOnTask>
  </Dependency>
  <Dependency>
    <Id>44</Id>
    <DependentTask>0</DependentTask>
    <DependsOnTask>11</DependsOnTask>
  </Dependency>
  <Dependency>
    <Id>45</Id>
    <DependentTask>0</DependentTask>
    <DependsOnTask>15</DependsOnTask>
  </Dependency>
  <Dependency>
    <Id>46</Id>
    <DependentTask>9</DependentTask>
    <DependsOnTask>4</DependsOnTask>
  </Dependency>
  <Dependency>
    <Id>47</Id>
    <DependentTask>9</DependentTask>
    <DependsOnTask>7</DependsOnTask>
  </Dependency>
  <Dependency>
    <Id>48</Id>
    <DependentTask>9</DependentTask>
    <DependsOnTask>8</DependsOnTask>
  </Dependency>
  <Dependency>
    <Id>49</Id>
    <DependentTask>9</DependentTask>
    <DependsOnTask>9</DependsOnTask>
  </Dependency>
  <Dependency>
    <Id>50</Id>
    <DependentTask>9</DependentTask>
    <DependsOnTask>11</DependsOnTask>
  </Dependency>
  <Dependency>
    <Id>53</Id>
    <DependentTask>12</DependentTask>
    <DependsOnTask>8</DependsOnTask>
  </Dependency>
  <Dependency>
    <Id>54</Id>
    <DependentTask>12</DependentTask>
    <DependsOnTask>12</DependsOnTask>
  </Dependency>
  <Dependency>
    <Id>55</Id>
    <DependentTask>12</DependentTask>
    <DependsOnTask>16</DependsOnTask>
  </Dependency>
  <Dependency>
    <Id>56</Id>
    <DependentTask>12</DependentTask>
    <DependsOnTask>17</DependsOnTask>
  </Dependency>
  <Dependency>
    <Id>57</Id>
    <DependentTask>12</DependentTask>
    <DependsOnTask>10</DependsOnTask>
  </Dependency>
  <Dependency>
    <Id>64</Id>
    <DependentTask>17</DependentTask>
    <DependsOnTask>5</DependsOnTask>
  </Dependency>
  <Dependency>
    <Id>65</Id>
    <DependentTask>11</DependentTask>
    <DependsOnTask>3</DependsOnTask>
  </Dependency>
  <Dependency>
    <Id>66</Id>
    <DependentTask>11</DependentTask>
    <DependsOnTask>4</DependsOnTask>
  </Dependency>
  <Dependency>
    <Id>67</Id>
    <DependentTask>11</DependentTask>
    <DependsOnTask>5</DependsOnTask>
  </Dependency>
  <Dependency>
    <Id>68</Id>
    <DependentTask>11</DependentTask>
    <DependsOnTask>8</DependsOnTask>
  </Dependency>
  <Dependency>
    <Id>69</Id>
    <DependentTask>11</DependentTask>
    <DependsOnTask>15</DependsOnTask>
  </Dependency>
  <Dependency>
    <Id>70</Id>
    <DependentTask>11</DependentTask>
    <DependsOnTask>1</DependsOnTask>
  </Dependency>
  <Dependency>
    <Id>71</Id>
    <DependentTask>11</DependentTask>
    <DependsOnTask>2</DependsOnTask>
  </Dependency>
  <Dependency>
    <Id>72</Id>
    <DependentTask>11</DependentTask>
    <DependsOnTask>10</DependsOnTask>
  </Dependency>
  <Dependency>
    <Id>73</Id>
    <DependentTask>11</DependentTask>
    <DependsOnTask>11</DependsOnTask>
  </Dependency>
  <Dependency>
    <Id>74</Id>
    <DependentTask>11</DependentTask>
    <DependsOnTask>12</DependsOnTask>
  </Dependency>
  <Dependency>
    <Id>75</Id>
    <DependentTask>18</DependentTask>
    <DependsOnTask>8</DependsOnTask>
  </Dependency>
  <Dependency>
    <Id>89</Id>
    <DependentTask>6</DependentTask>
    <DependsOnTask>3</DependsOnTask>
  </Dependency>
  <Dependency>
    <Id>90</Id>
    <DependentTask>6</DependentTask>
    <DependsOnTask>4</DependsOnTask>
  </Dependency>
  <Dependency>
    <Id>91</Id>
    <DependentTask>6</DependentTask>
    <DependsOnTask>5</DependsOnTask>
  </Dependency>
  <Dependency>
    <Id>92</Id>
    <DependentTask>6</DependentTask>
    <DependsOnTask>8</DependsOnTask>
  </Dependency>
  <Dependency>
    <Id>93</Id>
    <DependentTask>6</DependentTask>
    <DependsOnTask>16</DependsOnTask>
  </Dependency>
  <Dependency>
    <Id>94</Id>
    <DependentTask>6</DependentTask>
    <DependsOnTask>1</DependsOnTask>
  </Dependency>
  <Dependency>
    <Id>95</Id>
    <DependentTask>6</DependentTask>
    <DependsOnTask>2</DependsOnTask>
  </Dependency>
  <Dependency>
    <Id>96</Id>
    <DependentTask>14</DependentTask>
    <DependsOnTask>13</DependsOnTask>
  </Dependency>
  <Dependency>
    <Id>97</Id>
    <DependentTask>14</DependentTask>
    <DependsOnTask>11</DependsOnTask>
  </Dependency>
</ArrayOfDependency>